mcp_sentry_custom/__init__.py
mcp_sentry_custom/main.py
mcp_sentry_custom/server.py
mseep_mcp_sentry_custom-0.6.3.dist-info/METADATA
mseep_mcp_sentry_custom-0.6.3.dist-info/WHEEL
mseep_mcp_sentry_custom-0.6.3.dist-info/entry_points.txt
mseep_mcp_sentry_custom-0.6.3.dist-info/top_level.txt
mseep_mcp_sentry_custom-0.6.3.dist-info/RECORD
